{
    "file": "wire\/modules\/Inputfield\/InputfieldPageTitle\/InputfieldPageTitle.module",
    "textdomain": "wire--modules--inputfield--inputfieldpagetitle--inputfieldpagetitle-module",
    "translations": {
        "2864512e4161ae21b145798e32938abf": {
            "text": "Tytu\u0142 strony (Page Title)"
        },
        "dc643f0a55e724a742f7bcc43fa5b84e": {
            "text": "Pole dla tytu\u0142u stron, posiada tak\u017ce opcje automatycznego generowania nazw stron (gdy nazwa jest pusta)"
        }
    }
}